Metadata-Version: 2.1
Name: count-fgs-sam
Version: 1.0.dev7
Summary: Count Functional Genomics Screen alignments in a SAM file with filtering options
Home-page: https://gitlab.com/twlee79/count_fgs_sam
Author: Tet Woo Lee
Author-email: developer@twlee.nz
License: UNKNOWN
Platform: UNKNOWN
Classifier: Programming Language :: Python :: 3
Classifier: License :: OSI Approved :: GNU General Public License v3 (GPLv3)
Classifier: Operating System :: OS Independent
Requires-Dist: pysam (<0.19,>=0.15.4)
